MANIFEST.in
README.rst
setup.py
pyShipping_python3.egg-info/PKG-INFO
pyShipping_python3.egg-info/SOURCES.txt
pyShipping_python3.egg-info/dependency_links.txt
pyShipping_python3.egg-info/not-zip-safe
pyShipping_python3.egg-info/top_level.txt
pyshipping/__init__.py
pyshipping/addressvalidation.py
pyshipping/binpack.py
pyshipping/binpack_simple.py
pyshipping/package.py
pyshipping/shipment.py
pyshipping/carriers/__init__.py
pyshipping/carriers/dpd/__init__.py
pyshipping/carriers/dpd/georoute.py
pyshipping/carriers/dpd/georoute_test.py
pyshipping/carriers/dpd/georoutetables/COUNTRY
pyshipping/carriers/dpd/georoutetables/DEPOTS.gz
pyshipping/carriers/dpd/georoutetables/LOCATION.DE
pyshipping/carriers/dpd/georoutetables/LOCATION.EN
pyshipping/carriers/dpd/georoutetables/LOCATION.FR
pyshipping/carriers/dpd/georoutetables/ROUTES.gz
pyshipping/carriers/dpd/georoutetables/SERVICE
pyshipping/carriers/dpd/georoutetables/SERVICEINFO.CS
pyshipping/carriers/dpd/georoutetables/SERVICEINFO.CZ
pyshipping/carriers/dpd/georoutetables/SERVICEINFO.DE
pyshipping/carriers/dpd/georoutetables/SERVICEINFO.EE
pyshipping/carriers/dpd/georoutetables/SERVICEINFO.EN
pyshipping/fortras/__init__.py
pyshipping/fortras/bordero.py
pyshipping/fortras/entl.py
pyshipping/fortras/fakt.py
pyshipping/fortras/fortras_stat.py
pyshipping/fortras/test.py