Metadata-Version: 1.2
Name: pyShipping-python3
Version: 0.0.1
Summary: pyShipping - Shipping related Toolkit
Home-page: https://github.com/joncombe/pyShipping-python3
Maintainer: Jon Combe via Maximillian Dornseif
Maintainer-email: jon@naremit.com
License: UNKNOWN
Platform: UNKNOWN
Classifier: License :: OSI Approved :: BSD License
Classifier: Intended Audience :: Developers
Classifier: Programming Language :: Python
